aliyunsdkselectdb/__init__.py
aliyunsdkselectdb/request/__init__.py
aliyunsdkselectdb/request/v20230522/AllocateInstancePublicConnectionRequest.py
aliyunsdkselectdb/request/v20230522/CheckCreateDBInstanceRequest.py
aliyunsdkselectdb/request/v20230522/CheckServiceLinkedRoleRequest.py
aliyunsdkselectdb/request/v20230522/CreateDBClusterRequest.py
aliyunsdkselectdb/request/v20230522/CreateDBInstanceRequest.py
aliyunsdkselectdb/request/v20230522/CreateElasticRuleRequest.py
aliyunsdkselectdb/request/v20230522/CreateServiceLinkedRoleForSelectDBRequest.py
aliyunsdkselectdb/request/v20230522/DeleteDBClusterRequest.py
aliyunsdkselectdb/request/v20230522/DeleteDBInstanceRequest.py
aliyunsdkselectdb/request/v20230522/DeleteElasticRuleRequest.py
aliyunsdkselectdb/request/v20230522/DescribeAllDBInstanceClassRequest.py
aliyunsdkselectdb/request/v20230522/DescribeDBClusterConfigChangeLogsRequest.py
aliyunsdkselectdb/request/v20230522/DescribeDBClusterConfigRequest.py
aliyunsdkselectdb/request/v20230522/DescribeDBInstanceAttributeRequest.py
aliyunsdkselectdb/request/v20230522/DescribeDBInstanceNetInfoRequest.py
aliyunsdkselectdb/request/v20230522/DescribeDBInstancesRequest.py
aliyunsdkselectdb/request/v20230522/DescribeElasticRulesRequest.py
aliyunsdkselectdb/request/v20230522/DescribeSecurityIPListRequest.py
aliyunsdkselectdb/request/v20230522/EnDisableScalingRulesRequest.py
aliyunsdkselectdb/request/v20230522/GetCreateBEClusterInquiryRequest.py
aliyunsdkselectdb/request/v20230522/GetModifyBEClusterInquiryRequest.py
aliyunsdkselectdb/request/v20230522/ModifyBEClusterAttributeRequest.py
aliyunsdkselectdb/request/v20230522/ModifyDBClusterConfigRequest.py
aliyunsdkselectdb/request/v20230522/ModifyDBClusterRequest.py
aliyunsdkselectdb/request/v20230522/ModifyDBInstanceAttributeRequest.py
aliyunsdkselectdb/request/v20230522/ModifyElasticRuleRequest.py
aliyunsdkselectdb/request/v20230522/ModifySecurityIPListRequest.py
aliyun_python_sdk_selectdb-1.0.0.dist-info/LICENSE
aliyun_python_sdk_selectdb-1.0.0.dist-info/METADATA
aliyun_python_sdk_selectdb-1.0.0.dist-info/WHEEL
aliyun_python_sdk_selectdb-1.0.0.dist-info/top_level.txt
aliyun_python_sdk_selectdb-1.0.0.dist-info/RECORD
